<?xml version="1.0" encoding="UTF-8"?>
<b:beans xmlns="http://www.springframework.org/schema/security"
         xmlns:b="http://www.springframework.org/schema/beans"
         xmlns:xsi="http://www.w3.org/2001/XMLSchema-instance"
         xsi:schemaLocation="http://www.springframework.org/schema/beans http://www.springframework.org/schema/beans/spring-beans.xsd
		 http://www.springframework.org/schema/security http://www.springframework.org/schema/security/spring-security.xsd">

    <authentication-manager>
        <authentication-provider>
            <user-service>
                <user name="user" password="user123" authorities="ROLE_USER" />
            </user-service>
        </authentication-provider>
    </authentication-manager>

    <http auto-config='true' use-expressions="true">
        <form-login default-target-url="/secure.jsp" />
        <intercept-url pattern="/" access="isAnonymous()" />
        <intercept-url pattern="/index.jsp" access="isAnonymous()" />
        <intercept-url pattern="/secure.jsp" access="hasRole('ROLE_USER')" />
    </http>

</b:beans>